skshapes/__init__.py
skshapes/errors.py
skshapes/globals.py
skshapes/types.py
skshapes/utils.py
skshapes/applications/__init__.py
skshapes/applications/barycentric_landmark_setter.py
skshapes/applications/browser.py
skshapes/applications/vertices_landmark_setter.py
skshapes/applications/window_generator.py
skshapes/convolutions/__init__.py
skshapes/convolutions/constant_kernel.py
skshapes/convolutions/linear_operator.py
skshapes/convolutions/mesh_convolution.py
skshapes/convolutions/point_convolution.py
skshapes/convolutions/squared_distances.py
skshapes/data/__init__.py
skshapes/data/image.py
skshapes/data/polydata.py
skshapes/data/utils.py
skshapes/decimation/__init__.py
skshapes/decimation/decimation.py
skshapes/features/__init__.py
skshapes/features/curvatures.py
skshapes/features/implicit_quadrics.py
skshapes/features/moments.py
skshapes/features/normals.py
skshapes/features/structure_tensors.py
skshapes/input_validation/__init__.py
skshapes/input_validation/converters.py
skshapes/input_validation/notnone_rules.py
skshapes/input_validation/typechecking.py
skshapes/loss/__init__.py
skshapes/loss/baseloss.py
skshapes/loss/lp.py
skshapes/loss/nearest_neighbors.py
skshapes/loss/optimal_transport.py
skshapes/loss/varifold.py
skshapes/morphing/__init__.py
skshapes/morphing/basemodel.py
skshapes/morphing/extrinsic_deformation.py
skshapes/morphing/intrinsic_deformation.py
skshapes/morphing/rigid_motion.py
skshapes/morphing/validation.py
skshapes/multiscaling/__init__.py
skshapes/multiscaling/multiscale.py
skshapes/optimization/__init__.py
skshapes/tasks/__init__.py
skshapes/tasks/registration.py
skshapes/triangle_mesh/__init__.py
skshapes/triangle_mesh/edge_topology.py
skshapes/triangle_mesh/geometry.py
skshapes/triangle_mesh/shell_energy.py
skshapes-0.2.dist-info/LICENSE
skshapes-0.2.dist-info/METADATA
skshapes-0.2.dist-info/WHEEL
skshapes-0.2.dist-info/top_level.txt
skshapes-0.2.dist-info/RECORD
