Metadata-Version: 2.1
Name: skshapes
Version: 0.2
Summary: Shape analysis in python
License: MIT License
Project-URL: Documentation, https://scikit-shapes.github.io/scikit-shapes/
Project-URL: Repository, https://github.com/scikit-shapes/scikit-shapes
Requires-Python: >=3.10
License-File: LICENSE
Requires-Dist: torch
Requires-Dist: torchdiffeq
Requires-Dist: numpy
Requires-Dist: pykeops
Requires-Dist: geomloss
Requires-Dist: jaxtyping
Requires-Dist: beartype ==0.17.2
Requires-Dist: pyvista
Requires-Dist: vedo
Requires-Dist: fast-simplification
Requires-Dist: fast-edges-extraction
Provides-Extra: all
Requires-Dist: skshapes[taichi] ; extra == 'all'
Provides-Extra: taichi
Requires-Dist: taichi ; extra == 'taichi'
